CONTRIBUTING
LICENSE
MANIFEST.in
README.rst
requirements.txt
setup.py
RESTpy.egg-info/PKG-INFO
RESTpy.egg-info/SOURCES.txt
RESTpy.egg-info/dependency_links.txt
RESTpy.egg-info/requires.txt
RESTpy.egg-info/top_level.txt
restpy/__init__.py
restpy/api.py
restpy/context.py
restpy/applications/__init__.py
restpy/applications/base.py
restpy/applications/map.py
restpy/endpoints/__init__.py
restpy/endpoints/base.py
restpy/hooks/__init__.py
restpy/hooks/after/__init__.py
restpy/hooks/after/context.py
restpy/hooks/before/__init__.py
restpy/hooks/before/unique.py
restpy/middlewares/__init__.py
restpy/middlewares/context.py
restpy/middlewares/unique.py