Metadata-Version: 1.0
Name: RESTpy
Version: 0.7.1
Summary: Werkzeug extensions for building RESTful services.
Home-page: https://github.com/kevinconway/rest.py
Author: Kevin Conway
Author-email: kevinjacobconway@gmail.com
License: BSD
Platform: UNKNOWN
